tomegathericon/utils/logger/__init__.py
tomegathericon/utils/logger/classes/__init__.py
tomegathericon/utils/logger/classes/_logger_properties.py
tomegathericon/utils/logger/classes/level_filter.py
tomegathericon/utils/logger/classes/logger.py
tomegathericon/utils/logger/classes/py.typed
tomegathericon/utils/logger/exceptions/__init__.py
tomegathericon/utils/logger/exceptions/invalid_value_provided_error.py
tomegathericon/utils/logger/exceptions/logger_not_available_error.py
tomegathericon/utils/logger/exceptions/property_not_found_error.py
tomegathericon/utils/logger/exceptions/py.typed
tomegathericon/utils/logger/py.typed
tomegathericon_utils_logger-0.0.9.dist-info/METADATA
tomegathericon_utils_logger-0.0.9.dist-info/WHEEL
tomegathericon_utils_logger-0.0.9.dist-info/RECORD
