Metadata-Version: 2.3
Name: tomegathericon-utils-logger
Version: 0.0.9
Summary: Various Loggers
License: Software License Agreement
Author: Abhishek Kapoor
Author-email: kapoor.abhishek@outlook.com
Requires-Python: >=3.12,<4.0
Classifier: License :: Other/Proprietary License
Classifier: Programming Language :: Python :: 3
Classifier: Programming Language :: Python :: 3.12
Classifier: Programming Language :: Python :: 3.13
Requires-Dist: poetry-core (>=2.1.3,<3.0.0)
Requires-Dist: pydantic (>=2.11.7,<3.0.0)
Requires-Dist: pyfiglet (>=1.0.4,<2.0.0)
Requires-Dist: tomegathericon-utils-log-formatter (>=0.0.3,<0.0.4)
